wjordpress-0.2.2.dist-info/top_level.txt
wjordpress-0.2.2.dist-info/RECORD
wjordpress-0.2.2.dist-info/METADATA
wjordpress-0.2.2.dist-info/metadata.json
wjordpress-0.2.2.dist-info/DESCRIPTION.rst
wjordpress-0.2.2.dist-info/WHEEL
wjordpress/urls.py
wjordpress/views.py
wjordpress/__init__.py
wjordpress/managers.py
wjordpress/api.py
wjordpress/factories.py
wjordpress/dj_exten_jsonfield.py
wjordpress/admin.py
wjordpress/models.py
wjordpress/templates/wjordpress/widget.html
wjordpress/templates/admin/wjordpress/wplog/change_form.html
wjordpress/templatetags/__init__.py
wjordpress/templatetags/wjordpress.py
wjordpress/management/__init__.py
wjordpress/management/commands/wjordpress_fetch.py
wjordpress/management/commands/__init__.py
