Metadata-Version: 2.0
Name: wjordpress
Version: 0.2.2
Summary: Django integration with WordPress through the json-rest-api plugin
Home-page: https://github.com/texastribune/wjordpress
Author: Chris Chang
Author-email: cchang@texastribune.org
License: Apache License, Version 2.0
Platform: UNKNOWN
Classifier: Development Status :: 3 - Alpha
Classifier: Framework :: Django
Classifier: Intended Audience :: Developers
Classifier: License :: OSI Approved :: Apache Software License
Classifier: Programming Language :: Python :: 2
Classifier: Programming Language :: Python :: 2.7
Classifier: Programming Language :: Python :: 3
Classifier: Programming Language :: Python :: 3.3
Classifier: Programming Language :: Python :: 3.4
Requires-Dist: six (>=1.0.0)
